ptt_mail_backup/__init__.py
ptt_mail_backup/__main__.py
ptt_mail_backup/ansi.py
ptt_mail_backup/article.py
ptt_mail_backup/ptt_bot.py
ptt_mail_backup/pyte/__init__.py
ptt_mail_backup/pyte/__main__.py
ptt_mail_backup/pyte/charsets.py
ptt_mail_backup/pyte/control.py
ptt_mail_backup/pyte/escape.py
ptt_mail_backup/pyte/graphics.py
ptt_mail_backup/pyte/modes.py
ptt_mail_backup/pyte/screens.py
ptt_mail_backup/pyte/streams.py
ptt_mail_backup-0.6.0.dist-info/LICENSE
ptt_mail_backup-0.6.0.dist-info/METADATA
ptt_mail_backup-0.6.0.dist-info/WHEEL
ptt_mail_backup-0.6.0.dist-info/entry_points.txt
ptt_mail_backup-0.6.0.dist-info/top_level.txt
ptt_mail_backup-0.6.0.dist-info/zip-safe
ptt_mail_backup-0.6.0.dist-info/RECORD
