Metadata-Version: 2.1
Name: ptt-mail-backup
Version: 0.6.0
Summary: Backup PTT mail
Home-page: https://github.com/eight04/ptt-mail-backup
Author: eight
Author-email: eight04@gmail.com
License: MIT
Keywords: ptt,mail
Classifier: Development Status :: 4 - Beta
Classifier: Environment :: Console
Classifier: Intended Audience :: End Users/Desktop
Classifier: License :: OSI Approved :: MIT License
Classifier: Natural Language :: Chinese (Traditional)
Classifier: Programming Language :: Python :: 3
Classifier: Programming Language :: Python :: 3.7
Classifier: Programming Language :: Python :: 3.12
Classifier: Programming Language :: Python :: 3 :: Only
Classifier: Topic :: Communications :: BBS
License-File: LICENSE
Requires-Dist: paramiko ~=3.4
Requires-Dist: ptt-article-parser ~=0.6.0
Requires-Dist: uao ~=0.2.0
Requires-Dist: wcwidth ~=0.2.13
